client/__init__.py
client/add_contact.py
client/client_conv.py
client/database.py
client/del_contact.py
client/main_window.py
client/start_dialog.py
client/transport.py
client/common/__init__.py
client/common/decorator.py
client/common/utils.py
client/common/variables.py
client/log_project/__init__.py
client/log_project/config_client_log.py
client/log_project/config_server_log.py
client/unit_tests/__init__.py
client/unit_tests/log_decorator.py
client/unit_tests/test_client.py
client/unit_tests/test_server.py
client/unit_tests/test_utils.py
pyqt_messaging_client-0.0.1.dist-info/METADATA
pyqt_messaging_client-0.0.1.dist-info/WHEEL
pyqt_messaging_client-0.0.1.dist-info/top_level.txt
pyqt_messaging_client-0.0.1.dist-info/RECORD
