Metadata-Version: 2.1
Name: pyqt-messaging-client
Version: 0.0.1
Summary: PyQT GB Client
Home-page: UNKNOWN
Author: Zektornis
Author-email: shevchenko.logist@mail.ru
License: UNKNOWN
Platform: UNKNOWN
Requires-Dist: PyQt5
Requires-Dist: sqlalchemy
Requires-Dist: pycryptodome
Requires-Dist: pycryptodomex
